subpackage/__init__.py
subpackage/test.py
intel_cloud_data_connector-0.0.0.dev4.dist-info/LICENSE
intel_cloud_data_connector-0.0.0.dev4.dist-info/METADATA
intel_cloud_data_connector-0.0.0.dev4.dist-info/WHEEL
intel_cloud_data_connector-0.0.0.dev4.dist-info/top_level.txt
intel_cloud_data_connector-0.0.0.dev4.dist-info/RECORD
