Metadata-Version: 2.1
Name: intel-cloud-data-connector
Version: 0.0.0.dev4
Summary: Intel's cloud data connector
Author-email: Jose de Jesus Herrera Ledon <jesus.herrera.ledon@intel.com>, Alberto Gallegos Muro <alberto.gallegos.muro@intel.com>, Felipe Leza Alvarez <felipe.leza.alvarez@intel.com>, Miguel Pineda Juarez <miguel.pineda.juarez@intel.com>, Gerardo Dominguez Aldama <gerardo.dominguez.aldama@intel.com>
License: 
Classifier: Programming Language :: Python :: 3
Classifier: License :: OSI Approved :: Apache Software License
Classifier: Operating System :: OS Independent
Requires-Python: <3.11,>=3.8
License-File: LICENSE
Requires-Dist: azureml (>=0.2.7)
Requires-Dist: azure-ai-ml (>=1.4.0)
Requires-Dist: azure-storage-blob (>=12.14.1)
Requires-Dist: azure-identity (>=1.12.0)
Requires-Dist: azure-core (>=1.26.3)
Requires-Dist: azureml-core (>=1.49.0)
Requires-Dist: boto3 (>=1.26.65)
Requires-Dist: google-api-core (>=2.11.0)
Requires-Dist: google-auth (>=2.16.2)
Requires-Dist: google-auth-oauthlib (>=1.0.0)
Requires-Dist: google-cloud-bigquery (>=3.7.0)
Requires-Dist: google-cloud-storage (>=2.7.0)
Requires-Dist: packaging (<22.0,>=20.0)
Requires-Dist: python-dotenv (>=1.0.0)
